drf_commons/__init__.py
drf_commons/common_conf/__init__.py
drf_commons/common_conf/django_settings.py
drf_commons/common_conf/settings.py
drf_commons/common_conf/test_urls.py
drf_commons/common_tests/__init__.py
drf_commons/common_tests/base_cases.py
drf_commons/common_tests/conftest.py
drf_commons/common_tests/factories.py
drf_commons/common_tests/utils.py
drf_commons/common_tests/serializers/__init__.py
drf_commons/common_tests/serializers/base.py
drf_commons/common_tests/serializers/fields.py
drf_commons/current_user/__init__.py
drf_commons/current_user/apps.py
drf_commons/current_user/utils.py
drf_commons/current_user/tests/__init__.py
drf_commons/current_user/tests/test_utils.py
drf_commons/debug/__init__.py
drf_commons/debug/apps.py
drf_commons/debug/logger.py
drf_commons/debug/utils.py
drf_commons/debug/core/__init__.py
drf_commons/debug/core/categories.py
drf_commons/debug/logging/__init__.py
drf_commons/debug/logging/config.py
drf_commons/debug/logging/directories.py
drf_commons/debug/logging/formatters.py
drf_commons/debug/logging/handlers/__init__.py
drf_commons/debug/logging/handlers/specs.py
drf_commons/debug/logging/loggers/__init__.py
drf_commons/debug/logging/loggers/specs.py
drf_commons/debug/tests/__init__.py
drf_commons/debug/tests/test_categories.py
drf_commons/debug/tests/test_logger.py
drf_commons/debug/tests/test_utils.py
drf_commons/decorators/__init__.py
drf_commons/decorators/cache.py
drf_commons/decorators/database.py
drf_commons/decorators/logging.py
drf_commons/decorators/performance.py
drf_commons/decorators/tests/__init__.py
drf_commons/decorators/tests/test_cache.py
drf_commons/decorators/tests/test_database.py
drf_commons/decorators/tests/test_logging.py
drf_commons/decorators/tests/test_performance.py
drf_commons/filters/__init__.py
drf_commons/filters/apps.py
drf_commons/filters/ordering/__init__.py
drf_commons/filters/ordering/computed.py
drf_commons/filters/ordering/processors.py
drf_commons/filters/ordering/tests/__init__.py
drf_commons-1.0.1.dist-info/licenses/LICENSE
drf_commons-1.0.1.dist-info/METADATA
drf_commons-1.0.1.dist-info/WHEEL
drf_commons-1.0.1.dist-info/top_level.txt
drf_commons-1.0.1.dist-info/RECORD
