Metadata-Version: 2.4
Name: drf-commons
Version: 1.0.1
Summary: Django REST Framework Common Utilities - Modular apps for enhanced DRF functionality
Author: Victoire HABAMUNGU
Author-email: Victoire HABAMUNGU <contact@htvictoire.me>
License: MIT
Project-URL: Homepage, https://github.com/htvictoire/drf-common
Project-URL: Repository, https://github.com/htvictoire/drf-common
Project-URL: Issues, https://github.com/htvictoire/drf-common/issues
Keywords: django,rest-framework,drf,utilities,api
Classifier: Development Status :: 4 - Beta
Classifier: Intended Audience :: Developers
Classifier: License :: OSI Approved :: MIT License
Classifier: Operating System :: OS Independent
Classifier: Programming Language :: Python :: 3
Classifier: Programming Language :: Python :: 3.8
Classifier: Programming Language :: Python :: 3.9
Classifier: Programming Language :: Python :: 3.10
Classifier: Programming Language :: Python :: 3.11
Classifier: Programming Language :: Python :: 3.12
Classifier: Programming Language :: Python :: 3.13
Classifier: Framework :: Django
Classifier: Framework :: Django :: 3.2
Classifier: Framework :: Django :: 4.0
Classifier: Framework :: Django :: 4.1
Classifier: Framework :: Django :: 4.2
Classifier: Framework :: Django :: 5.0
Classifier: Framework :: Django :: 5.1
Requires-Python: >=3.8
License-File: LICENSE
Requires-Dist: Django>=3.2
Requires-Dist: djangorestframework>=3.12
Provides-Extra: current-user
Provides-Extra: debug
Provides-Extra: filters
Provides-Extra: pagination
Provides-Extra: response
Provides-Extra: serializers
Provides-Extra: views
Provides-Extra: export
Requires-Dist: openpyxl>=3.0; extra == "export"
Requires-Dist: weasyprint>=60.0; extra == "export"
Provides-Extra: import
Requires-Dist: openpyxl>=3.0; extra == "import"
Requires-Dist: pandas>=1.3; extra == "import"
Provides-Extra: config
Requires-Dist: django-constance>=2.9; extra == "config"
Provides-Extra: all
Requires-Dist: openpyxl>=3.0; extra == "all"
Requires-Dist: weasyprint>=60.0; extra == "all"
Requires-Dist: pandas>=1.3; extra == "all"
Requires-Dist: django-constance>=2.9; extra == "all"
Provides-Extra: dev
Requires-Dist: black==25.1.0; extra == "dev"
Requires-Dist: flake8==7.3.0; extra == "dev"
Requires-Dist: isort==6.0.1; extra == "dev"
Requires-Dist: mypy==1.18.1; extra == "dev"
Provides-Extra: test
Requires-Dist: pytest==8.4.2; extra == "test"
Requires-Dist: pytest-cov==7.0.0; extra == "test"
Requires-Dist: pytest-django==4.11.1; extra == "test"
Requires-Dist: factory-boy>=3.3; extra == "test"
Provides-Extra: build
Requires-Dist: build>=1.0; extra == "build"
Requires-Dist: twine>=6.0; extra == "build"
Dynamic: author
Dynamic: license-file
Dynamic: requires-python
